[
  {
    "title": "Watch the Titanic and Lusitania Sink in Real Time: One Fast, One Slow",
    "url": "https://www.openculture.com/2026/04/watch-the-titanic-and-lusitania-sink-in-real-time-one-fast-one-slow.html",
    "image": "https://cdn8.openculture.com/2026/04/02234402/Screenshot-2026-04-02-at-11.45.15-PM-1024x547.png",
    "tag": "Culture",
    "date": "2026-04-03T08:00:44.000Z",
    "description": "\n\tin History |   \tApril 3rd, 2026  1 Comment\n\t\n\t\t\t\n\n\t\n\nAsked to name famous ship­wrecks at a bar triv­ia night, a fair few par­tic­i­pants might think",
    "body": "\n\tin History |   \tApril 3rd, 2026  1 Comment\n\t\n\t\t\t\n\n\t\n\nAsked to name famous ship­wrecks at a bar triv­ia night, a fair few par­tic­i­pants might think imme­di­ate­ly of Pearl Har­bor, whether or not they can recall that it was the USS Ari­zona bombed there. More firm­ly with­in liv­ing mem­o­ry sits the SS Andrea Doria, though she’s hard­ly the cul­tur­al ref­er­ence she used to be. The wreck of the SS Edmund Fitzger­ald passed its fifti­eth anniver­sary just last year, which gave a boost to its remem­brance, if most­ly by Gor­don Light­foot fans. There is, of course, the Endurance, though the ship her­self has always been over­shad­owed by the efforts of her cap­tain to get the whole crew home alive. The schooner Hes­pe­rus does come to mind as a par­tic­u­lar­ly unfor­tu­nate ves­sel, per­haps all the more so because she did­n’t actu­al­ly exist.\nNear­ly every­one at the bar is, of course, going to put down the RMS Titan­ic first. Even before she received the James Cameron treat­ment, that “unsink­able” ocean lin­er was eas­i­ly the most famous ship­wreck of the twen­ti­eth cen­tu­ry, and quite pos­si­bly of all his­to­ry. But sec­ond place has to go to the RMS Lusi­ta­nia, which went under just three years after the Titan­ic. As close as the year 1915 may sound to 1912, devel­op­ments in Europe had rearranged the world in the mean­time. The Titan­ic met her end by col­lid­ing with an ice­berg, and about two and a half hours lat­er, as you can see in the real-time sink­ing video at the top of the post, it was on the bot­tom of the North Atlantic. When the Lusi­ta­nia was tor­pe­doed by a Ger­man U‑boat, by con­trast, she went down in just eigh­teen min­utes.\nYou can wit­ness those min­utes re-cre­at­ed in the ani­mat­ed video from Ocean­lin­er Designs just above. Though the Great War was rag­ing, the ship had­n’t yet been com­mis­sioned as an armed mer­chant cruis­er, but was con­duct­ing her usu­al transat­lantic pas­sen­ger ser­vice while — as the Ger­man side insist­ed and the British at first denied — car­ry­ing war mate­ri­als on the side. She’d been trav­el­ing due east for six days when U‑20 sight­ed her; after an hour of track­ing came the launch of the fate­ful under­wa­ter mis­sile and its 160-kilo­gram explo­sive pay­load. The video shows and explains not just how the Lusi­ta­nia slipped below the water, but also the break­down along the way of her var­i­ous struc­tur­al ele­ments and mechan­i­cal sys­tems, includ­ing the ele­va­tors that had once seemed such mar­velous inno­va­tions.\n\n\n\t\n\nIt seems that after the tor­pe­do hit, prac­ti­cal­ly every­thing that could have con­se­quent­ly gone wrong did, right down to the few deploy­able lifeboats drop­ping cat­a­stroph­i­cal­ly from their davits. The crew of the Titan­ic man­aged to launch most of her lifeboats, but there weren’t enough of them in the first place. That con­tributed to a final death toll of around 1,500, as com­pared with 1,197 on the Lusi­ta­nia. Though sim­i­lar in scale and his­tor­i­cal tim­ing, these two mar­itime dis­as­ters end­ed up with very dif­fer­ent mean­ings. The wreck of the Titan­ic con­tin­ues to cap­ture imag­i­na­tions by res­onat­ing with the indus­tri­al romance, class strat­i­fi­ca­tion, and impe­r­i­al hubris of the long nine­teenth cen­tu­ry; that of the Lusi­ta­nia, whose sink­ing played a major role in bring­ing the Unit­ed States into what we now call World War I, shows us noth­ing so clear­ly as the mer­ci­less geopo­lit­i­cal log­ic of the twen­ti­eth.\nRelat­ed con­tent:\nWatch the Sink­ing of the Lusi­ta­nia Ani­mat­ed in Real Time (1915)\nHow James Cameron Shot Titan­ic’s Huge­ly Com­plex Sink­ing Scene\nThe Sink­ing of the Bri­tan­nic: An Ani­mat­ed Intro­duc­tion to the Titanic’s For­got­ten Sis­ter Ship\nThe Cos­ta Con­cor­dia Ship­wreck Viewed from Out­er Space\nThe First Full 3D Scan of the Titan­ic, Made of More Than 700,000 Images Cap­tur­ing the Wreck’s Every Detail\nA New 3D Scan, Cre­at­ed from 25,000 High-Res­o­lu­tion Images, Reveals the Remark­ably Well-Pre­served Wreck of Shackleton’s Endurance\nBased in Seoul, Col­in Marshall writes and broad­casts on cities, lan­guage, and cul­ture. He’s the author of the newslet­ter Books on Cities as well as the books 한국 요약 금지 (No Sum­ma­riz­ing Korea) and Kore­an Newtro. Fol­low him on the social net­work for­mer­ly known as Twit­ter at @colinmarshall.\n\t\t\n        \t",
    "schema": {
      "@context": "https://schema.org",
      "@type": "NewsArticle",
      "headline": "Watch the Titanic and Lusitania Sink in Real Time: One Fast, One Slow",
      "image": [
        "https://cdn8.openculture.com/2026/04/02234402/Screenshot-2026-04-02-at-11.45.15-PM-1024x547.png"
      ],
      "datePublished": "2026-04-03T08:00:44.000Z",
      "dateModified": "2026-04-03T08:00:44.000Z",
      "author": [
        {
          "@type": "Person",
          "name": "Midnight Ink Staff"
        }
      ]
    }
  },
  {
    "title": "Misato Sano's Charming Wooden Dogs Are Carved With Personality",
    "url": "https://www.thisiscolossal.com/2026/04/misato-sano-wooden-dog-sculptures/",
    "image": "https://www.thisiscolossal.com/wp-content/uploads/2026/04/sano-9.jpg",
    "tag": "Culture",
    "date": "2026-04-03T20:03:09.000Z",
    "description": "\n\n\t\nMisato Sano’s studio is replete with piles of wooden offcuts, heavy lumber, woodworking equipment, and flowing natural light. The Miyagi-based art",
    "body": "\n\n\t\nMisato Sano’s studio is replete with piles of wooden offcuts, heavy lumber, woodworking equipment, and flowing natural light. The Miyagi-based artist has been sculpting charismatic dogs for several years, steadily adding more distinct characters to her growing pack.\nSelf-portraiture remains a consistent theme within Sano’s practice. Each dog evokes a different emotion mirroring the artist’s personality, ranging from shy and skittish to excited and silly. “Visualizing my inner self through expressions and gestures full of charm and humor has also become an opportunity to deepen my self-love,” she shares.\n“I Got a Good Idea!” (2025)\nSano’s distinctive woodcarving techniques are exemplary of the artist’s signature style. Dimpled surfaces, for instance, evoke different types of dog coats and allow for color variance to come through upon the finishing application of oil paint. Working with camphor wood, the sculptural exaggeration of physical features such as limbs, bulbous tufts of fur, and even nails add to the body of work’s playful appeal.\nThese rhythmic textures and amusing design choices have also lent themselves to explorations of embroidery and illustration. Meditative stitches and repetitive, gridded ink drawings are a continuation of the artist’s dialogue with herself.\nSano is gearing up for an exciting year. Later this month, her work will be on view in a duo exhibition at the Kan Hai Art Museum in Taiwan. In August, the artist’s work is traveling to the states for Nucleus Portland’s 10th anniversary show, before a third exhibition at Igoone Arai in her native Miyagi, Japan. Keep up with the artist’s tail-wagging adventures by following her on Instagram.\n“Raspberry” (2025)\n“I’ve Got a Feeling” (2024)\n“Bamboo Shoot Crazy” (2025)\n“Let’s go, BOSCH!” (2025)\n“Sweet Dreams” (2022)\n“Rice Cake Pekingese” (2025)\n“Wrinkly Pug” (2025)\n“Captain Yorkie” (2025)\nFrom the artist’s “Drawing Series” (2025)\n“The Forgetful Whippet” (2025)\n“Wear a Ribbon and Look Fashionable” (2024)\n\t\n\t\n\t",
    "schema": {
      "@context": "https://schema.org",
      "@type": "NewsArticle",
      "headline": "Misato Sano's Charming Wooden Dogs Are Carved With Personality",
      "image": [
        "https://www.thisiscolossal.com/wp-content/uploads/2026/04/sano-9.jpg"
      ],
      "datePublished": "2026-04-03T20:03:09.000Z",
      "dateModified": "2026-04-03T20:03:09.000Z",
      "author": [
        {
          "@type": "Person",
          "name": "Midnight Ink Staff"
        }
      ]
    }
  },
  {
    "title": "Brushstrokes Transform into Beaded Topographies in Liza Lou's Mixed-Media Paintings",
    "url": "https://www.thisiscolossal.com/2026/04/liza-lou-faq-beaded-paintings/",
    "image": "https://www.thisiscolossal.com/wp-content/uploads/2026/04/lou-4-e1775221913929.jpg",
    "tag": "Culture",
    "date": "2026-04-03T15:18:07.000Z",
    "description": "\n\n\t\nOne of the many reasons artists like Lee Krasner, Jackson Pollock, Franz Kline, Cy Twombly, and other mid-20th-century pioneers of painterly abstr",
    "body": "\n\n\t\nOne of the many reasons artists like Lee Krasner, Jackson Pollock, Franz Kline, Cy Twombly, and other mid-20th-century pioneers of painterly abstraction were so innovative for their time is the use of the deliberate yet loose brushstroke. Pollock intuitively dribbled and splattered paint on surfaces spread across the floor of his studio, and Kline created bold, monochromatic paintings with just a few deceptively simple, gestural strokes of a large brush. It’s this visceral approach to visual rhythms and color that continues to awe us today. (A major retrospective highlighting both Krasner and Pollock’s work is slated for The Met later this year.)\nFor artist Liza Lou, the calculation of brushstrokes, color, and gesture opens the door to another media type altogether—beads. The artist is known for using the material, including a large-scale installation titled “Kitchen,” which took five years to create. In her recent work, she adds thousands of the diminutive baubles in myriad colors, shapes, and sizes to sweeps of oil paint on canvas. Tapping into the legacy of Abstract Expressionism, Lou parses the relationship between gesture, intention, organic forms, and the brushstroke as a subject unto itself.\nDetail of “Enjambment”\nLou’s works appear this month in FAQ, a solo exhibition at Thaddaeus Ropac. The title references questions that the artist returns to again and again in her practice. When does a painting become not a painting? Can a brushstroke be more than a brushstroke? “These works are about amplification—about making things more ideal,” Lou says. “There’s a poem by Fernando Pessoa where he writes about wanting flowers to be more flowers than flowers, and in this body of work I’m using my material as a way to make paint more paint than paint.”\nUnlike a quick swipe of a brush, each bead is meticulously placed amid a field of others, creating a chromatic topography. Lou likens them to painting “straight-out-of-the-tube,” except that they can’t be mixed on the canvas. She relies on color relationships, textures, and precise placement to give the impression that, from a distance, the loose strokes and splatters have blended or merged. When viewed up close, we see distinct, saturated topographies that, in a rather macro sense, are delightfully sculptural with the soft ground of painted details underneath. “My process involves this improv where every stroke requires everything I have, my full attention,” Lou says. “Every mark becomes this kind of violin-crescendo-holy shit-experience.”\nFAQ opens on April 10 and continues through May 23 in London. See more on Lou’s Instagram.\n“Onomatopoeia” (2026), oil paint and glass beads on stretched canvas, 52 x 51 x 1.75 inches\nDetail of “Onomatopoeia”\n“Analepsis” (2025), oil paint and glass beads on stretched canvas, 42.75 x 41.75 x 1.75 inches\nDetail of “Analepsis”\n“Stanza” (2025), oil paint and glass beads on. stretched canvas, 52 x 51 x 1.75 inches\nDetail of “Stanza”\n“Ecphonesis” (2026), oil paint and glass beads on stretched canvas, 42.75 x 41.75 x 1.75 inches\n\t\n\t\n\t",
    "schema": {
      "@context": "https://schema.org",
      "@type": "NewsArticle",
      "headline": "Brushstrokes Transform into Beaded Topographies in Liza Lou's Mixed-Media Paintings",
      "image": [
        "https://www.thisiscolossal.com/wp-content/uploads/2026/04/lou-4-e1775221913929.jpg"
      ],
      "datePublished": "2026-04-03T15:18:07.000Z",
      "dateModified": "2026-04-03T15:18:07.000Z",
      "author": [
        {
          "@type": "Person",
          "name": "Midnight Ink Staff"
        }
      ]
    }
  },
  {
    "title": "Explore Art UK's Digital Database of More Than 6,600 Street Art Murals",
    "url": "https://www.thisiscolossal.com/2026/04/art-uk-digital-database-street-art-murals/",
    "image": "https://www.thisiscolossal.com/wp-content/uploads/2026/04/artuk-6.jpg",
    "tag": "Culture",
    "date": "2026-04-03T12:56:38.000Z",
    "description": "\n\n\t\nThe surprise of turning onto a street to see a vibrant mural—or the joy of viewing several in progress during popular festivals like Nuart Aberdee",
    "body": "\n\n\t\nThe surprise of turning onto a street to see a vibrant mural—or the joy of viewing several in progress during popular festivals like Nuart Aberdeen—is essentially an ephemeral experience. Murals may be designed to last several decades, or they may be temporary installations that address a particularly interesting bit of local history or urgent social issue, but either way, the experience is brief as we walk by. Always vulnerable to the elements and new development, these pieces don’t always last long. That’s where Art UK’s archive comes in.\nAs a digital platform, Art UK connects viewers to public collections around the nation. There are about a million artworks on the site, drawn from around 3,500 collections, including museums, libraries, hospitals, town halls, and more. The organization also recently reached a significant milestone in its ambition to map and catalogue street art and murals across the country. Just a little more than two years after launching the initiative, Art UK has added more than 6,600 new works to its database, bringing the total number of public artworks to well over 21,000.\nKarl Read, “Building Peace” (2024), West Street, Bristol. © the artist. Photo by Paul Francis / Art UK\nRanging from small, spray-painted pieces by the notoriously enigmatic Banksy to large-scale compositions by Rogue-one, The London Mural Company, and more, the scope is daunting. “Our initial aim for the project was simple: we wanted to record 5,000 murals and wall-based artworks from across the U.K.,” says Art UK’s Public Art Manager, Tracy Jenkins. “The artworks would date from A.D. 1000 to the present day and include wall paintings in historic churches, post-war ceramic and concrete works, and contemporary painted murals and mosaics.”\nVolunteers dedicated more than 5,000 hours to locating and photographing the works. The database includes many that are decades old at this point, emphasizing their sites and condition in case they’re ever threatened by future redevelopments. Most of the works are relatively recent, but Art UK doesn’t discriminate based on date or even if they’re outside. A series of otherworldly paintings inside of St. Thomas’ Church in East Shefford, Berkshire, for example, are centuries old.\nJenkins notes that the project launched at a time when street art and mural-making in the U.K. were experiencing a boom, and the addition of these aesthetic installations within an urban context “has been shown to significantly reduce the instances of unsightly tagging graffiti,” in addition to boosting visitors and local economies. She also acknowledges “public art in any form can be contentious, sparking debate and strong emotion… Street art and muralism is in many ways the most democratic genre—it is not created in a faraway studio, it is not locked behind closed doors, and it does not require prior expert knowledge.”\nCreating an archive of street art and murals is a way to build engagement and also understanding of the medium, promoting a feeling of what Jenkins calls “community ownership and pride,” where moments of artistic, informative, playful, and celebratory work delight around city corners. See a handful of additions below, and explore the database on Art UK’s website.\nZabou, “Gordon Gibbens (1931–2017)” (2020), Bycroft Street, Penge, Bromley. © the artist. Photo by Mike Longhurst / Art UK\nRob Fenton, “Get Home Safe” (2024), Scarlett Street, Newcastle-under-Lyme, Staffordshire. © the artist. Photo by Katey Goodwin / Art UK\nKevin Mc Hugh, “The Leap” (2023), Main Street, Belleek, County Fermanagh. © the artist. Photo by Jenny Owen / Art UK\nUnknown artist, Murals at St Thomas’ Church, East Shefford, (1100–1530s), Churches Conservation Trust. Photo by Dennis Jeffrey / Art UK\nAnnatomix, “A Bit of Parklife” (2024), Alcester Road, Birmingham, West Midlands. © the artist. Photo by David Blower / Art UK\nRogue-one, “Alexander Fleming (1881-1955)” (2025), East Main Street, Darvel, East Ayrshire. © the artist. Photo by Gordon Baird / Art UK\nFipsi Seilern / PANG, “Madge Gill (1882–1961)” (2019), Palmerston Road, Waltham Forest. © the artist. Photo by David Ovenden / Art UK\n\t\n\t\n\t",
    "schema": {
      "@context": "https://schema.org",
      "@type": "NewsArticle",
      "headline": "Explore Art UK's Digital Database of More Than 6,600 Street Art Murals",
      "image": [
        "https://www.thisiscolossal.com/wp-content/uploads/2026/04/artuk-6.jpg"
      ],
      "datePublished": "2026-04-03T12:56:38.000Z",
      "dateModified": "2026-04-03T12:56:38.000Z",
      "author": [
        {
          "@type": "Person",
          "name": "Midnight Ink Staff"
        }
      ]
    }
  },
  {
    "title": "Lebanese Artist Accuses Israel of War Crime for Strike That Killed His Parents",
    "url": "https://hyperallergic.com/lebanese-artist-accuses-israel-of-war-crime-for-strike-that-killed-his-parents/",
    "image": "https://storage.ghost.io/c/51/f8/51f871d8-b6be-4a73-b958-0ca4fff0110a/content/images/size/w1200/2026/04/GettyImages-1240175021.jpg",
    "tag": "Culture",
    "date": "2026-04-03T20:32:15.000Z",
    "description": "\n    \n                News\n                “We have to break this cycle of impunity,\" Ali Cherri, who filed a complaint against Israel in France’s War",
    "body": "\n    \n                News\n                “We have to break this cycle of impunity,\" Ali Cherri, who filed a complaint against Israel in France’s War Crimes Unit, told Hyperallergic.\n            \n                \n                                \n                            \n                \n            \n                \n        \n            Ali Cherri receiving a Silver Lion award at the 59th Venice Biennale on April 23, 2022 (photo Felix Hörhager/picture alliance via Getty Images)\n    \n        \n            Paris-based Lebanese filmmaker and artist Ali Cherri has formally accused the Israeli military of committing a war crime for a bombing that killed his parents inside their Beirut apartment in 2024.In the hours before a ceasefire between Hezbollah and Israel was set to take effect on November 26, 2024, Cherri’s parents, Mahmoud Naim Cherri and Nadira Hayek, were killed by an Israeli bomb that struck their 12-story residential building. The strike also killed the couple’s employee, Birki Negesa, and at least four others. Cherri, represented by the International Federation for Human Rights (FIDH), filed a war crimes complaint against the attack’s perpetrators in France’s War Crimes Unit yesterday, April 2.In his complaint, which the FIDH declined to share with Hyperallergic for confidentiality reasons, Cherri and FIDH accused unnamed individuals of the “war crime of intentionally directing an attack against a civilian object.” Under French law, this accusation carries a 15-year prison sentence. France has the authority to investigate the bombing of the apartment because Cherri is a dual citizen of France and Lebanon and owns the apartment building, FIDH said. The court does not have authority to directly prosecute the killing of Cherri’s parents, however.“What I hope from this procedure is that the truth is established, that this crime is named for what it is, and that those responsible are held accountable,” Cherri told Hyperallergic in an email. “We have to break this cycle of impunity.”In an analysis produced for the complaint, the London research agency Forensic Architecture found that two GBU-39 munitions, weapons engineered for precise targeting, were responsible for the strike. The weapon is manufactured in the United States and frequently used by Israel and other allies, Forensic Architecture noted in its 36-page report. Amnesty International also published an investigation in February. It found no evidence of a legitimate military target near the site of the bombing, and noted that no evacuation orders were issued in the area at that time.According to Amnesty International, Mahmoud Naim Cherri’s brother represented Hezbollah in parliament, but did not live in the building. Cherri, a mini-market owner, and his brother Emad, who was also injured in the attack, had no noted affiliations with the organization. Asked which avenues of justice he considered after the killing of his parents, Ali said legal action in France, as opposed to Lebanon, where the government has refused to join the International Criminal Court (ICC), made the most sense.“I don’t really see what other avenues for justice there are beyond filing a complaint in a country where I live, France, and whose nationality I hold,” Cherri told Hyperallergic. “It seems like the most logical and legitimate step any victim would take.”Maxime Illuzzi Duriez, a spokesperson for FIDH, said in an email that the organization hopes the complaint will prompt a judicial investigation that would identify the military and political perpetrators of the strike, so that the court could eventually issue arrest warrants.“These procedures are particularly lengthy and complex and take several years,” Duriez said. “We will be accompanying Ali Cherri throughout this whole process.”France’s War Crimes Unit, established in 2012, has previously issued arrest warrants for former Syrian dictator Bashar al-Assad and his associates for crimes perpetrated against French citizens. The court has also reviewed crimes tied to the Liberian civil war and the Rwandan genocide.Cherri’s films, sculpture, and two-dimensional artworks frequently examine the visceral impacts of political violence on the body. His works are held in the collections of major institutions around the world, including the Guggenheim Museum, the Museum of Modern Art, and the Centre Pompidou.“We are calling for an investigation to be opened, to establish the facts and understand what happened, not only for me and my family, but for all the other victims,” Cherri told Hyperallergic. “If this process can help prevent other families from going through the same loss, then it must be pursued,” he said.\n                  \n                      \n                        News\n                      \n                      \n                        Ali Cherri\n                      \n                      \n                        Lebanon\n                      \n                      \n                        Beirut\n                      \n                      \n                        Israel\n                      \n                  \n        \n    \n",
    "schema": {
      "@context": "https://schema.org",
      "@type": "NewsArticle",
      "headline": "Lebanese Artist Accuses Israel of War Crime for Strike That Killed His Parents",
      "image": [
        "https://storage.ghost.io/c/51/f8/51f871d8-b6be-4a73-b958-0ca4fff0110a/content/images/size/w1200/2026/04/GettyImages-1240175021.jpg"
      ],
      "datePublished": "2026-04-03T20:32:15.000Z",
      "dateModified": "2026-04-03T20:32:15.000Z",
      "author": [
        {
          "@type": "Person",
          "name": "Midnight Ink Staff"
        }
      ]
    }
  },
  {
    "title": "A View From the Easel",
    "url": "https://hyperallergic.com/a-view-from-the-easel-331/",
    "image": "https://storage.ghost.io/c/51/f8/51f871d8-b6be-4a73-b958-0ca4fff0110a/content/images/size/w1200/2026/04/gandini-studio-1---antonella-gandini-1.jpg",
    "tag": "Culture",
    "date": "2026-04-03T19:17:17.000Z",
    "description": "\n            Welcome to the 331st installment of A View From the Easel, a series in which artists reflect on their workspace. This week, artists reach",
    "body": "\n            Welcome to the 331st installment of A View From the Easel, a series in which artists reflect on their workspace. This week, artists reach a flow state through the hum of industrial fans and luxuriate in the silence of the Italian countryside.Want to take part? Check out our submission guidelines and share a bit about your studio with us through this form! All mediums and workspaces are welcome, including your home studio.Antonella Gandini, Monzambano, ItalyHow long have you been working in this space?Since 1980.Describe an average day in your studio.My studio is very quiet. I love the silence of the countryside, which produces a sort of expectation in me. I look at the things that are scattered around and I always find a good reason to start or complete a work. The essential element is the surprise of what happens. I don't foresee certain results, but I welcome the provocation of the material and the form.How does the space affect your work?I have the opportunity to leave various works scattered around. The space is very large and allows me to accumulate various objects, which gaze back at me for long periods of time until, suddenly, they suggest a solution that I embrace with enthusiasm.How do you interact with the environment outside your studio?Yes, there are several artists working in my area with whom I maintain a strong collaborative relationship — at times involving a mutual exchange of ideas. They work in diverse genres, not only painting and photography but also music and cinema, which creates excellent opportunities for teamwork. I am also a member of an association of female photographers spread across the country. I maintain an ongoing relationship with them, and together we organize exhibitions and events — often related to themes of gender — to raise public awareness regarding unresolved social and political issues, such as violence against women.What do you love about your studio?The tranquility, but also the opportunity to invite artists and friends to stay and work together. The space offers the chance to both exhibit and create, as has already been done on numerous occasions through group exhibitions, gatherings, and dialogues.What do you wish were different?If it were closer to a large city, it would certainly be more convenient for me to get around. However, I might lose the atmosphere of the place where I have always lived and which I love.What is your favorite local museum?I find Palazzo Te in Mantova to be a place of great inspiration.What is your favorite art material to work with?I currently work with photography, but I really enjoy drawing — minimizing the medium to better understand its potential.Diego Zarraga, Purchase, New YorkHow long have you been working in this space?One year.Describe an average day in your studio.I typically begin work at around 11am on a full studio day, and these drag until late at night. My practice consists of observational drawings, small paintings, and sometimes collages that then graduate to a large-scale piece that prioritizes movement and full-body movements. The day begins by boiling water to make coffee and clean brushes. From here, I sit down in front of the paintings I am aiming to work on and decide what needs to be developed that day.Sometimes, my energy is distributed among all the works I have up in the studio, allowing for conversations between colors and making the paintings come out looking like families. I usually listen to music or watch podcasts on topics that will distract me enough to reach an autopilot mode when painting, allowing me to not overthink my choices and just react to what is in front of me. Not sure if this is a type of sensory overload, but I find that if my other senses are engaged in one way or another, my mind can take over.How does the space affect your work?The space is communal among seniors at Purchase College and MFA students. There is storage for stretcher bars in the back, so sometimes the rest of the undergrads will walk by. I find that whenever I reach this \"flow state,\" seeing people walk by the studio or someone yelling (they do this often) takes me out of the zone. Besides that, the industrial building has the constant noise of fans spinning and sometimes resetting, a sort of static that also creates enough noise to make listening to one's thoughts a bit easier. How do you interact with the environment outside your studio?I think I am somewhat disconnected from the local artist community, both because of the nature of my work and because I commute to the college as opposed to the vast majority of people in the studio, who live on campus. Despite this, I find that being isolated from the rest of urban New York allows for more vibrant colors and quiet moments to appear and converse among my paintings. What do you love about your studio?I love that it has these huge windows facing northeast that allow the sunrise to peak through into the studios and the sunset to cast a cool light into the windows in the afternoon. They usually turn a warm blue color that is impossible to miss in the grey spectrum of color found in these spaces.What do you wish were different?I wish it were a little bigger, and sometimes I wish I had a door so I wouldn't feel observed when painting. But I think I will miss feeling like I'm in a zoo cage after I graduate.What is your favorite local museum?The Neuberger Museum of Art!What is your favorite art material to work with?Oil paints.\n                  \n                      \n                        Community\n                      \n                      \n                        A View From the Easel\n                      \n                  \n        ",
    "schema": {
      "@context": "https://schema.org",
      "@type": "NewsArticle",
      "headline": "A View From the Easel",
      "image": [
        "https://storage.ghost.io/c/51/f8/51f871d8-b6be-4a73-b958-0ca4fff0110a/content/images/size/w1200/2026/04/gandini-studio-1---antonella-gandini-1.jpg"
      ],
      "datePublished": "2026-04-03T19:17:17.000Z",
      "dateModified": "2026-04-03T19:17:17.000Z",
      "author": [
        {
          "@type": "Person",
          "name": "Midnight Ink Staff"
        }
      ]
    }
  },
  {
    "title": "Matzah Is the Medium",
    "url": "https://hyperallergic.com/matzah-is-the-medium/",
    "image": "/assets/images/news/default.jpg",
    "tag": "Culture",
    "date": "2026-04-03T10:00:16.000Z",
    "description": "\n    \n                Daily Newsletter\n                Remembering Melvin Edwards, art shows to see in LA and New York, and lessons from Houston’s Pro",
    "body": "\n    \n                Daily Newsletter\n                Remembering Melvin Edwards, art shows to see in LA and New York, and lessons from Houston’s Project Row Houses.\n            \n                \n                                \n                            \n                \n            \n        \n            Happy Passover! As matzah appears on Seder tables across the world this week, artist Emily Drew Miller approaches the flatbread as a printmaking tool. Her collagraph series tenderly explores Jewish heritage and political consciousness in all its fractures and layers. Staff Reporter Isa Farfan has the story.Today, we also remember the unflinching life and work of sculptor Melvin Edwards, who died on Monday at 88 years old and leaves behind a singular political vocabulary in steel. Don’t forget to check out our Los Angeles and New York guides to help plan your April in art, plus Senior Editor Valentina Di Liscia’s weekly dispatch on news in the art world this week — including improbable artworks made from beloved, gelatinous PEEPS, just in time for Easter.—Lakshmi Rivera Amin, associate editor\nWorks in the ongoing Mazot series (photos courtesy Emily Drew Miller)An Artist Embraces the Metaphorical Cracks of Matzah“ The fractures in these images reflect how disconnected a lot of Jewish people feel from each other right now,” Emily Drew Miller told Hyperallergic. | Isa Farfan\n                    \n                    \n                    \n                        \n                            Summer Marathons in Painting and Drawing at the New York Studio SchoolJoin an immersive, two-week session and transform your studio practice. Online or in-person.\n                        \n                        \n                            Learn more\n                        \n                    \n            In MemoriamMelvin Edwards with “Fragment Dimension” (1962–63), c. 1963 (© 2026 Melvin Edwards; photo by and courtesy Melvin Edwards)Melvin Edwards, Who Sculpted a New Vocabulary for Political Art, Dies at 88His innovative abstractions evoked both the art historical canon and the haunting afterlives of Atlantic slavery. | Cat DawsonArt GuidesChris “DAZE” Ellis, “Gem Spa in the 80s” (2025) on display at PPOW Gallery (photo Hrag Vartanian/Hyperallergic)15 Shows to See in New York City This AprilMargaret Curtis’s deconstruction of American myth, quotidian objects by Marsden Hartley, and Wendy Red Star’s bead-inspired installation are among our picks. | Hrag Vartanian, Hakim Bishara, Seph Rodney, and Valentina Di Liscia10 Art Shows to See in Los Angeles This AprilDavid Alekhuogie’s defiant collage, Hannah Tishkoff’s visual poetry, an iconic Angeleno printmaking studio, portraits of Palestinian journalists, and more. | Matt StrombergBooksEmilio Martínez Poppe, installation view of Civic Views in the Philadelphia City Hall Courtyard, curated by Jameson Paige, 2025 (photo Albert Yee, courtesy Mural Arts Philadelphia)Nine Lessons on My Path From Engagement to LeadershipMy career has been defined by a steady effort to collapse silos: between curatorial and educational work, between institutions and communities, between what museums have been and what they might yet become. | Ryan N. Dennis\n                    \n                    \n                    \n                        \n                            Vilcek Foundation to Award $200,000 in Grants to Nonprofits Uplifting Immigrant ContributionsThe foundation invites grant applications from mission-aligned nonprofit organizations in the arts and sciences by April 30, 2026.\n                        \n                        \n                            Learn more\n                        \n                    \n            Puppets dedicated to the Abuelas de Plaza de Mayo in Buenos Aires, Argentina (© Nahuel Ignacio Sánchez Painequir)Art Movements: Frieze Partners With ... the Whitney?Also, the IAIA Museum of Contemporary Native Arts director retires, the Speed Museum’s newest residents, and “peep” this art!Required ReadingThis week: Calida Rawles paints Blackness and water, the artists who shaped Fire Island, translating literature during the Tehran blackout, why weather apps suck, and more from around the internet.Jozanne Rabyor on Lakshmi Rivera Amin's \"A View From the Easel\":A choice pair, and when I clicked on the site, those fabulous faces behind Jade Van Der Mark's sofa lifted my spirits before I read a word. I hope they get their pig!I also hope Lex Marie gets their degree and more space to work. Personally, I'll treasure their observation that \"the ideas themselves do not have to shrink just because the space is smaller.\" Brilliant, and methinks it applies to making art and so much more!\n\n                        Commenting privileges are reserved for paid members. Join us today!\n                    \nOpportunities This MonthJohn Singer Sargent, “An Artist at His Easel” (1914) (image courtesy the Art Institute of Chicago)Residencies, fellowships, grants, and open calls from Banff Centre, the Vilcek Foundation, and more in our April 2026 list of opportunities for artists, writers, and art workers.Receive this list of opportunities in your inbox each month. Sign up here!\n                  \n                      \n                        Daily Newsletter\n                      \n                      \n                        Newsletter\n                      \n                  \n        \n    \n",
    "schema": {
      "@context": "https://schema.org",
      "@type": "NewsArticle",
      "headline": "Matzah Is the Medium",
      "image": [
        "/assets/images/news/default.jpg"
      ],
      "datePublished": "2026-04-03T10:00:16.000Z",
      "dateModified": "2026-04-03T10:00:16.000Z",
      "author": [
        {
          "@type": "Person",
          "name": "Midnight Ink Staff"
        }
      ]
    }
  }
]